{
	"type":"origins:multiple",
	"hidden":true,
	"exists":{
		"type":"origins:resource",
		"min":0,
		"max":1
	},
	"create_new":{
		"type":"origins:active_self",
		"entity_action":{
			"type":"origins:and",
			"actions":[
				{
					"type":"origins:execute_command",
					"command":"function origins-plus-plus:light-mage/create_pocket_dimension"
				},
				{
					"type":"origins:delay",
					"ticks":10,
					"action":{
						"type":"origins:execute_command",
						"command":"function origins-plus-plus:light-mage/effects"
					}
				}
			]
		},
		"key":"key.loadToolbarActivator",
		"condition":{
			"type":"origins:and",
			"conditions":[
				{
					"type":"origins:sneaking",
					"inverted":true
				},
				{
					"type":"origins:equipped_item",
					"equipment_slot":"offhand",
					"item_condition":{
						"type":"origins:ingredient",
						"ingredient":{
							"item":"minecraft:lodestone"
						}
					}
				}
			]
		}
	},
	"go_to":{
		"type":"origins:active_self",
		"entity_action":{
			"type":"origins:and",
			"actions":[
				{
					"type":"origins:execute_command",
					"command":"function origins-plus-plus:light-mage/go_to_pocket_dimension"
				},
				{
					"type":"origins:delay",
					"ticks":10,
					"action":{
						"type":"origins:execute_command",
						"command":"function origins-plus-plus:light-mage/effects"
					}
				}
			]
		},
		"key":"key.origins.primary_active",
		"condition":{
			"type":"origins:and",
			"conditions":[
				{
					"type":"origins:sneaking",
					"inverted":true
				},
				{
					"type":"origins:equipped_item",
					"equipment_slot":"offhand",
					"item_condition":{
						"type":"origins:ingredient",
						"ingredient":{
							"item":"minecraft:lodestone"
						}
					}
				},
				{
					"type":"origins:resource",
					"resource":"origins-plus-plus:light-mage/pocket_dimension_exists",
					"comparison":"==",
					"compare_to":1
				}
			]
		}
	},
	"bring_to":{
		"type":"origins:active_self",
		"entity_action":{
			"type":"origins:and",
			"actions":[
				{
					"type":"origins:execute_command",
					"command":"function origins-plus-plus:light-mage/bring_to_pocket_dimension"
				},
				{
					"type":"origins:delay",
					"ticks":10,
					"action":{
						"type":"origins:execute_command",
						"command":"tag @e[distance=0..3] remove tppocket"
					}
				},
				{
					"type":"origins:delay",
					"ticks":10,
					"action":{
						"type":"origins:execute_command",
						"command":"function origins-plus-plus:light-mage/effects"
					}
				}
			]
		},
		"key":"key.origins.primary_active",
		"condition":{
			"type":"origins:and",
			"conditions":[
				{
					"type":"origins:sneaking"
				},
				{
					"type":"origins:equipped_item",
					"equipment_slot":"offhand",
					"item_condition":{
						"type":"origins:ingredient",
						"ingredient":{
							"item":"minecraft:lodestone"
						}
					}
				},
				{
					"type":"origins:resource",
					"resource":"origins-plus-plus:light-mage/pocket_dimension_exists",
					"comparison":"==",
					"compare_to":1
				}
			]
		}
	},
	"go_back":{
		"type":"origins:active_self",
		"entity_action":{
			"type":"origins:and",
			"actions":[
				{
					"type":"origins:execute_command",
					"command":"function origins-plus-plus:light-mage/bring_back_from_pocket_dimension"
				},
				{
					"type":"origins:delay",
					"ticks":10,
					"action":{
						"type":"origins:execute_command",
						"command":"kill @e[distance=..5,type=minecraft:armor_stand,tag=back]"
					}
				},
				{
					"type":"origins:delay",
					"ticks":10,
					"action":{
						"type":"origins:execute_command",
						"command":"function origins-plus-plus:light-mage/effects"
					}
				}
			]
		},
		"key":"key.origins.secondary_active",
		"condition":{
			"type":"origins:and",
			"conditions":[
				{
					"type":"origins:sneaking",
					"inverted":true
				},
				{
					"type":"origins:equipped_item",
					"equipment_slot":"offhand",
					"item_condition":{
						"type":"origins:ingredient",
						"ingredient":{
							"item":"minecraft:lodestone"
						}
					}
				},
				{
					"type":"origins:dimension",
					"dimension":"minecraft:the_nether"
				}
			]
		}
	},
	"bring_back":{
		"type":"origins:active_self",
		"entity_action":{
			"type":"origins:and",
			"actions":[
				{
					"type":"origins:execute_command",
					"command":"function origins-plus-plus:light-mage/bring_back_from_pocket_dimension"
				},
				{
					"type":"origins:delay",
					"ticks":10,
					"action":{
						"type":"origins:execute_command",
						"command":"tag @e[distance=0..3] remove tppocket"
					}
				},
				{
					"type":"origins:delay",
					"ticks":10,
					"action":{
						"type":"origins:execute_command",
						"command":"kill @e[distance=..5,type=minecraft:armor_stand,tag=back]"
					}
				},
				{
					"type":"origins:delay",
					"ticks":10,
					"action":{
						"type":"origins:execute_command",
						"command":"function origins-plus-plus:light-mage/effects"
					}
				}
			]
		},
		"key":"key.origins.secondary_active",
		"condition":{
			"type":"origins:and",
			"conditions":[
				{
					"type":"origins:sneaking"
				},
				{
					"type":"origins:equipped_item",
					"equipment_slot":"offhand",
					"item_condition":{
						"type":"origins:ingredient",
						"ingredient":{
							"item":"minecraft:lodestone"
						}
					}
				},
				{
					"type":"origins:dimension",
					"dimension":"minecraft:the_nether"
				}
			]
		}
	}
}