{
	"type":"origins:multiple",
	"heal_copper":{
		"type":"origins:action_over_time",
		"interval":50,
		"entity_action":{
			"type":"origins:and",
			"actions":[
				{
					"type":"origins:heal",
					"amount":3
				},
				{
					"type":"origins:execute_command",
					"command":"clear @s minecraft:copper_ingot 1"
				}
			]
		},
		"condition":{
			"type":"origins:and",
			"conditions":[
				{
					"type":"origins:equipped_item",
					"equipment_slot":"offhand",
					"item_condition":{
						"type":"origins:ingredient",
						"ingredient":{
							"item":"minecraft:copper_ingot"
						}
					}
				},
				{
					"type":"origins:health",
					"comparison":"<",
					"compare_to":20
				}
			]
		}
	},
	"heal_iron":{
		"type":"origins:action_over_time",
		"interval":50,
		"entity_action":{
			"type":"origins:and",
			"actions":[
				{
					"type":"origins:heal",
					"amount":3
				},
				{
					"type":"origins:execute_command",
					"command":"clear @s minecraft:iron_ingot 1"
				}
			]
		},
		"condition":{
			"type":"origins:and",
			"conditions":[
				{
					"type":"origins:equipped_item",
					"equipment_slot":"offhand",
					"item_condition":{
						"type":"origins:ingredient",
						"ingredient":{
							"item":"minecraft:iron_ingot"
						}
					}
				},
				{
					"type":"origins:health",
					"comparison":"<",
					"compare_to":20
				}
			]
		}
	},
	"heal_iron_nugget":{
		"type":"origins:action_over_time",
		"interval":50,
		"entity_action":{
			"type":"origins:and",
			"actions":[
				{
					"type":"origins:heal",
					"amount":1
				},
				{
					"type":"origins:execute_command",
					"command":"clear @s minecraft:iron_nugget 1"
				}
			]
		},
		"condition":{
			"type":"origins:and",
			"conditions":[
				{
					"type":"origins:equipped_item",
					"equipment_slot":"offhand",
					"item_condition":{
						"type":"origins:ingredient",
						"ingredient":{
							"item":"minecraft:iron_nugget"
						}
					}
				},
				{
					"type":"origins:health",
					"comparison":"<",
					"compare_to":20
				}
			]
		}
	}
}