{
	"powers": [
		"origins:climbing",
		"origins:scare_creepers",
		"origins-plus-plus:binturong/blast_damage",
		"origins-plus-plus:binturong/effects",
		"origins-plus-plus:binturong/fallimmune",
		"origins-plus-plus:binturong/fire",
		"origins-plus-plus:binturong/flight",
		"origins-plus-plus:binturong/frail",
		"origins-plus-plus:binturong/invisibility",
		"origins-plus-plus:binturong/jockey",
		"origins-plus-plus:binturong/jumpboost",
		"origins-plus-plus:binturong/junglenative",
		"origins-plus-plus:binturong/lowground",
		"origins-plus-plus:binturong/lowground",
		"origins-plus-plus:binturong/maniac_digger",
		"origins-plus-plus:binturong/nimble",
		"origins-plus-plus:binturong/nocturnal",
		"origins-plus-plus:binturong/phantomize",
		"origins-plus-plus:binturong/pounce",
		"origins-plus-plus:binturong/shake",
		"origins-plus-plus:binturong/small_stature",
		"origins-plus-plus:binturong/sounds",
		"origins-plus-plus:binturong/sugar_rush",
		"origins-plus-plus:binturong/tooheavy"
	],
	"icon": "minecraft:cocoa_beans",
	"impact": 2,
	"name": "Binturong",
	"description": "A binturong is a bear cat of the trees."
}
