{
	"powers": [
		"origins-plus-plus:insect/anklebite",
		"origins-plus-plus:insect/climbing",
		"origins-plus-plus:insect/falldamage",
		"origins-plus-plus:insect/flap",
		"origins-plus-plus:insect/reach",
		"origins-plus-plus:insect/health",
		"origins-plus-plus:insect/height",
		"origins-plus-plus:insect/small",
		"origins-plus-plus:insect/rain_slowness",
		"origins-plus-plus:insect/water_slowness",
		"origins-plus-plus:insect/speed",
		"origins-plus-plus:insect/lava",
		"origins-plus-plus:insect/water"
	],
	"icon": "minecraft:vine",
	"order": 10,
	"impact": 2,
	"name": "Insect",
	"description": "The people who have evolved to live with the insects."
}
