{
	"powers": [
		"origins:tailwind",
		"origins:slow_falling",
		"origins-plus-plus:sporeling/decomposer",
		"origins-plus-plus:sporeling/firedamage",
		"origins-plus-plus:sporeling/healthdecrease",
		"origins-plus-plus:sporeling/jockey",
		"origins-plus-plus:sporeling/light_armor",
		"origins-plus-plus:sporeling/poison_spread_attack",
		"origins-plus-plus:sporeling/poison_spread_attack_particles",
		"origins-plus-plus:sporeling/poison_spread_attack_sound",
		"origins-plus-plus:sporeling/poison_spread_attack_sound_additional",
		"origins-plus-plus:sporeling/poison_spread_attack_sound_additional_extra",
		"origins-plus-plus:sporeling/smallspeed",
		"origins-plus-plus:sporeling/tinyspore",
		"origins-plus-plus:sporeling/updraft",
		"origins-plus-plus:sporeling/updraft_particles"
	],
	"icon": "minecraft:brown_mushroom",
	"impact": 3,
	"name": "Sporeling",
	"description": "A tiny floaty mushroom-man that came out of the ground and started doing stuff.",
	"upgrades": [
		{
			"condition": "minecraft:end/kill_dragon",
			"origin": "origins-plus-plus:shroomling",
			"announcement": "After killing the ender dragon, you've grown into your final form: A small mushroom!"
		}
	]
}
