{
	"type":"origins:multiple",
	"pickaxe":{
    "type": "origins:item_on_item",
    "on_item_condition": {
        "type": "origins:ingredient",
		"ingredient": {
			"item":"minecraft:netherite_pickaxe"
		}
    },
    "using_item_condition": {
        "type": "origins:ingredient",
        "ingredient": {
            "item": "minecraft:bedrock"
        }
    },
    "result_from_on_stack": 1,
    "result": {
        "item": "minecraft:netherite_pickaxe",
        "tag": "{display:{Name:'{\"text\":\"Bedrockeans Will\",\"color\":\"dark_red\",\"italic\":false}',Lore:['{\"text\":\"This embodies all the power\",\"color\":\"red\",\"italic\":false}','{\"text\":\"of the bedrockean.\",\"color\":\"red\",\"italic\":false}']},HideFlags:3,Unbreakable:1,Enchantments:[{id:efficiency,lvl:7},{id:fortune,lvl:5},{id:sharpness,lvl:11},{id:fire_aspect,lvl:2},{id:looting,lvl:3},{id:vanishing_curse,lvl:1}],AttributeModifiers:[{AttributeName:\"generic.attack_speed\",Name:\"generic.attack_speed\",Amount:-2.4,Operation:0,UUID:[I;-79137801,-255767939,-1654395540,1566283193],Slot:\"mainhand\"},{AttributeName:\"generic.movement_speed\",Name:\"generic.movement_speed\",Amount:+0.025,Operation:0,UUID:[I;789928899,1744717332,-1283217849,-503666754],Slot:\"mainhand\"}],Bedrockeans_Will:1b}",
		"amount":1
    },
    "using_item_action": {
        "type": "origins:consume",
        "amount": 1
    },
	"on_item_action":{
        "type": "origins:consume",
        "amount": 1
    },
	"result_item_action":{
		"type":"origins:modify",
		"modifier":"origins-plus-plus:bedrockean/pickaxe"
	},
	"entity_action": {
    "type": "origins:and",
    "actions": [
      {
        "type": "origins:play_sound",
        "sound": "minecraft:block.anvil.use",
        "volume": 2,
        "pitch": 0.6
      },
      {
        "type": "origins:delay",
        "ticks": 25,
        "action": {
          "type": "origins:play_sound",
          "sound": "minecraft:block.enchantment_table.use",
          "volume": 3,
          "pitch": 0.75
        }
      }
    ]
	}
	},
	"keep":{
		"type":"origins:action_over_time",
		"entity_action":{
			"type":"origins:execute_command",
			"command":"kill @e[type=item, nbt={Item:{tag:{Bedrockeans_Will:1b}}}]"
		},
		"interval":5
	},
	"storage":{
		"type":"origins:action_over_time",
		"entity_action":{
			"type":"origins:and",
			"actions":[
			{
			"type":"origins:execute_command",
			"command":"data remove block ~ ~ ~1 Items[{id:\"minecraft:netherite_pickaxe\",tag:{Bedrockeans_Will:1b}}]"
			},
			{
			"type":"origins:execute_command",
			"command":"data remove block ~ ~ ~-1 Items[{id:\"minecraft:netherite_pickaxe\",tag:{Bedrockeans_Will:1b}}]"
			},
			{
			"type":"origins:execute_command",
			"command":"data remove block ~ ~ ~2 Items[{id:\"minecraft:netherite_pickaxe\",tag:{Bedrockeans_Will:1b}}]"
			},
			{
			"type":"origins:execute_command",
			"command":"data remove block ~ ~ ~-2 Items[{id:\"minecraft:netherite_pickaxe\",tag:{Bedrockeans_Will:1b}}]"
			},
			{
			"type":"origins:execute_command",
			"command":"data remove block ~1 ~ ~ Items[{id:\"minecraft:netherite_pickaxe\",tag:{Bedrockeans_Will:1b}}]"
			},
			{
			"type":"origins:execute_command",
			"command":"data remove block ~-1 ~ ~ Items[{id:\"minecraft:netherite_pickaxe\",tag:{Bedrockeans_Will:1b}}]"
			},
			{
			"type":"origins:execute_command",
			"command":"data remove block ~2 ~ ~ Items[{id:\"minecraft:netherite_pickaxe\",tag:{Bedrockeans_Will:1b}}]"
			},
			{
			"type":"origins:execute_command",
			"command":"data remove block ~-2 ~ ~ Items[{id:\"minecraft:netherite_pickaxe\",tag:{Bedrockeans_Will:1b}}]"
			},
			{
			"type":"origins:execute_command",
			"command":"data remove block ~ ~1 ~ Items[{id:\"minecraft:netherite_pickaxe\",tag:{Bedrockeans_Will:1b}}]"
			},
			{
			"type":"origins:execute_command",
			"command":"data remove block ~ ~2 ~ Items[{id:\"minecraft:netherite_pickaxe\",tag:{Bedrockeans_Will:1b}}]"
			},
			{
			"type":"origins:execute_command",
			"command":"data remove block ~ ~-1 ~ Items[{id:\"minecraft:netherite_pickaxe\",tag:{Bedrockeans_Will:1b}}]"
			},
			{
			"type":"origins:execute_command",
			"command":"data remove block ~ ~-2 ~ Items[{id:\"minecraft:netherite_pickaxe\",tag:{Bedrockeans_Will:1b}}]"
			}
			]
		},
		"interval":5
	},
	"name":"Forge",
	"description":"Use bedrock on a nethrite pickaxe to unlock your true potential."
}